{
  "updated": "2026-04-27T08:21:12.109Z",
  "items": [
    {
      "id": 37680,
      "title": "Live coverage: SpaceX to launch final ViaSat-3 satellite on Falcon Heavy rocket",
      "url": "https://spaceflightnow.com/2026/04/27/live-coverage-spacex-to-launch-final-viasat-3-satellite-on-falcon-heavy-rocket/",
      "image_url": "http://spaceflightnow.com/wp-content/uploads/2023/04/20230430fhviasatpre1-678x452.jpg",
      "source": "Spaceflight Now",
      "published_at": "2026-04-27"
    },
    {
      "id": 37679,
      "title": "SpaceX set to launch Falcon Heavy on Monday after 18 month hiatus",
      "url": "https://www.nasaspaceflight.com/2026/04/viasat-3-f3-falcon-heavy/",
      "image_url": "https://www.nasaspaceflight.com/wp-content/uploads/2026/04/DSC07904-scaled.jpeg",
      "source": "NASASpaceflight",
      "published_at": "2026-04-26"
    },
    {
      "id": 37678,
      "title": "Curiosity Rover uncovers fresh organic clues on Ancient Mars",
      "url": "https://www.nasaspaceflight.com/2026/04/nasas-curiosity-rover-organic-clues-mars/",
      "image_url": "https://www.nasaspaceflight.com/wp-content/uploads/2026/04/NSF-2026-04-26-20-06-48-645.jpg",
      "source": "NASASpaceflight",
      "published_at": "2026-04-26"
    },
    {
      "id": 37677,
      "title": "What’s Happening in Space Policy April 26-May 2, 2026",
      "url": "https://spacepolicyonline.com/news/whats-happening-in-space-policy-april-26-may-2-2026/",
      "image_url": "https://spacepolicyonline.com/wp-content/uploads/2026/04/Scott-Pace-GW-photo-Apr-2026-197x300.png",
      "source": "SpacePolicyOnline.com",
      "published_at": "2026-04-26"
    },
    {
      "id": 37676,
      "title": "Live Coverage: SpaceX to fly 25 Starlink satellites on its 50th Falcon 9 launch of the year",
      "url": "https://spaceflightnow.com/2026/04/26/live-coverage-spacex-to-fly-25-starlink-satellites-on-its-50th-falcon-9-launch-of-the-year/",
      "image_url": "http://spaceflightnow.com/wp-content/uploads/2026/03/20260329_20260313_Starlink_G17_31.jpg",
      "source": "Spaceflight Now",
      "published_at": "2026-04-26"
    },
    {
      "id": 37675,
      "title": "Progress MS-34 to launch from Baikonur for ISS cargo delivery",
      "url": "https://www.nasaspaceflight.com/2026/04/progress-ms34/",
      "image_url": "https://www.nasaspaceflight.com/wp-content/uploads/2026/04/IMG_9490.png",
      "source": "NASASpaceflight",
      "published_at": "2026-04-25"
    },
    {
      "id": 37674,
      "title": "I Am Artemis: Peter Rossoni",
      "url": "https://www.nasa.gov/missions/artemis/i-am-artemis/i-am-artemis-peter-rossoni/",
      "image_url": "https://www.nasa.gov/wp-content/uploads/2026/04/img-0068-edited-1.jpg",
      "source": "NASA",
      "published_at": "2026-04-24"
    },
    {
      "id": 37673,
      "title": "The Day of the Trifid Nebula",
      "url": "https://www.nasa.gov/image-article/the-day-of-the-trifid-nebula/",
      "image_url": "https://www.nasa.gov/wp-content/uploads/2026/04/full-res-for-display.png",
      "source": "NASA",
      "published_at": "2026-04-24"
    }
  ]
}